odoo/addons/sale_order_revision/README.rst
odoo/addons/sale_order_revision/__init__.py
odoo/addons/sale_order_revision/__manifest__.py
odoo/addons/sale_order_revision/i18n/es.po
odoo/addons/sale_order_revision/i18n/fr.po
odoo/addons/sale_order_revision/i18n/it.po
odoo/addons/sale_order_revision/i18n/sale_order_revision.pot
odoo/addons/sale_order_revision/models/__init__.py
odoo/addons/sale_order_revision/models/sale_order.py
odoo/addons/sale_order_revision/readme/CONTRIBUTORS.rst
odoo/addons/sale_order_revision/readme/DESCRIPTION.rst
odoo/addons/sale_order_revision/readme/INSTALL.rst
odoo/addons/sale_order_revision/static/description/icon.png
odoo/addons/sale_order_revision/static/description/index.html
odoo/addons/sale_order_revision/tests/__init__.py
odoo/addons/sale_order_revision/tests/test_sale_order_revision.py
odoo/addons/sale_order_revision/view/sale_order.xml
odoo14_addon_sale_order_revision-14.0.1.1.1.dist-info/METADATA
odoo14_addon_sale_order_revision-14.0.1.1.1.dist-info/WHEEL
odoo14_addon_sale_order_revision-14.0.1.1.1.dist-info/top_level.txt
odoo14_addon_sale_order_revision-14.0.1.1.1.dist-info/RECORD
